{
  "Ламинат": [
    "- 8мм",
    "- 10мм",
    "- 12мм",
    "Кварцвенил"
  ],
  "Линолеум": [
    "До 700р за квадратный метр",
    "От 700 до 1000 за квадрат ",
    "От 1000 и вышел"
  ],
  "Межкомнатные двери": [
    "До 10 тыс комплект",
    "До 15 тыс комплект",
    "До 20 тыс комплект",
    "От 20 тыс и выше"
  ],
  "Металические двери": [
    "Стандартные",
    "Двустворчатые"
  ],
  "Обои": [
    "Бюджетный сегмент",
    "Средний сегмент",
    "Дорогой сегмент"
  ],
  "Сантехника": [
    "Унитазы",
    "Раковина",
    "Душевая кабина",
    "Душевые ограждения",
    "Мебель",
    "Зеркала",
    "Ванны",
    "Пеналы мебельные"
  ],
  "Плитка": [
    "- Акция",
    "- 60/60",
    "- 60/120",
    "- 40/40",
    "- 45/45",
    "- 27/40",
    "- Плитка на ванну"
  ],
  "Галтели": [
    "С узорами",
    "Без узоров"
  ],
  "Плинтуса": [
    "Обычные",
    "Дюрополимеры",
    "Под покраску"
  ],
  "Техника мелкая": [
    "Техника мелко-бытовая",
    "Пылесосы для дома",
    "Пылесос строительный",
    "Измельчители",
    "Чайники",
    "Утюги",
    "Блендеры",
    "Робот пылесос и вертикальный пылесос",
    "Мясорубка",
    "Мультиварка",
    "Хлебопечка",
    "Термопоты",
    "Весы для кухни",
    "Микроволновки",
    "Поверхности газовые ",
    "Вытяжки",
    "Духовки отдельностоящие",
    "Миксеры"
  ],
  "Техника крупная": [],
  "Смесители": [
    "Для кухни",
    "Для раковины",
    "Для душа",
    "Душ обычный",
    "Душ тропический"
  ],
  "Ручки межкомнатные": [
    "До 1000р",
    "До 1500р",
    "1500р и выше"
  ],
  "Ручки металлические": [
    "Бюджетный сегмент",
    "Средний сегмент",
    "Дорогой сегмент"
  ],
  "Раковины для кухни": [],
  "Коврики для ванны": [],
  "Точечный свет": []
}